MANIFEST.in
README.rst
setup.py
screamshotter/__init__.py
screamshotter/settings.py
screamshotter/urls.py
screamshotter/wsgi.py
screamshotter.egg-info/PKG-INFO
screamshotter.egg-info/SOURCES.txt
screamshotter.egg-info/dependency_links.txt
screamshotter.egg-info/requires.txt
screamshotter.egg-info/top_level.txt