Metadata-Version: 1.1
Name: screamshotter
Version: 1.1.0
Summary: Web pages capture server
Home-page: https://github.com/makinacorpus/django-screamshot
Author: Mathieu Leplatre
Author-email: mathieu.leplatre@makina-corpus.com
License: UNKNOWN
Platform: UNKNOWN
Classifier: Natural Language :: English
Classifier: Operating System :: OS Independent
Classifier: Environment :: Web Environment
Classifier: Framework :: Django
Classifier: Programming Language :: Python :: 2.7
